smart_bot_factory/__init__.py
smart_bot_factory/cli.py
smart_bot_factory/config.py
smart_bot_factory/utm_link_generator.py
smart_bot_factory/admin/__init__.py
smart_bot_factory/admin/admin_events.py
smart_bot_factory/admin/admin_events_edit.py
smart_bot_factory/admin/admin_events_utils.py
smart_bot_factory/admin/admin_logic.py
smart_bot_factory/admin/admin_manager.py
smart_bot_factory/admin/states.py
smart_bot_factory/admin/timeout_checker.py
smart_bot_factory/analytics/analytics_manager.py
smart_bot_factory/configs/growthmed-october-24/prompts/1sales_context.txt
smart_bot_factory/configs/growthmed-october-24/prompts/2product_info.txt
smart_bot_factory/configs/growthmed-october-24/prompts/3objection_handling.txt
smart_bot_factory/configs/growthmed-october-24/prompts/final_instructions.txt
smart_bot_factory/configs/growthmed-october-24/prompts/help_message.txt
smart_bot_factory/configs/growthmed-october-24/prompts/welcome_message.txt
smart_bot_factory/configs/growthmed-october-24/reports/test_20250924_064229.txt
smart_bot_factory/configs/growthmed-october-24/reports/test_20250924_064335.txt
smart_bot_factory/configs/growthmed-october-24/reports/test_20250924_064638.txt
smart_bot_factory/configs/growthmed-october-24/tests/quick_scenarios.yaml
smart_bot_factory/configs/growthmed-october-24/tests/realistic_scenarios.yaml
smart_bot_factory/configs/growthmed-october-24/tests/scenario_examples.yaml
smart_bot_factory/configs/growthmed-october-24/welcome_file/welcome_file_msg.txt
smart_bot_factory/configs/growthmed-october-24/welcome_file/Чек лист по 152ФЗ и 323ФЗ для медицины.pdf
smart_bot_factory/creation/__init__.py
smart_bot_factory/creation/bot_builder.py
smart_bot_factory/creation/bot_testing.py
smart_bot_factory/dashboard/__init__.py
smart_bot_factory/event/__init__.py
smart_bot_factory/event/router.py
smart_bot_factory/event/router_manager.py
smart_bot_factory/event/decorators/__init__.py
smart_bot_factory/event/decorators/admin.py
smart_bot_factory-1.1.16.dist-info/METADATA
smart_bot_factory-1.1.16.dist-info/WHEEL
smart_bot_factory-1.1.16.dist-info/entry_points.txt
smart_bot_factory-1.1.16.dist-info/licenses/LICENSE
smart_bot_factory-1.1.16.dist-info/RECORD
