Metadata-Version: 2.4
Name: smart-bot-factory
Version: 1.1.16
Summary: Библиотека для создания умных чат-ботов
Author-email: Kopatych <eserov73@gmail.com>
License: MIT
License-File: LICENSE
Keywords: chatbot,cli,openai,supabase,telegram
Classifier: Development Status :: 4 - Beta
Classifier: Environment :: Console
Classifier: Framework :: AsyncIO
Classifier: Intended Audience :: Developers
Classifier: License :: OSI Approved :: MIT License
Classifier: Operating System :: OS Independent
Classifier: Programming Language :: Python :: 3
Classifier: Programming Language :: Python :: 3.10
Classifier: Programming Language :: Python :: 3.11
Classifier: Programming Language :: Python :: 3.12
Classifier: Topic :: Communications :: Chat
Classifier: Topic :: Software Development :: Libraries :: Python Modules
Requires-Python: >=3.10
Requires-Dist: aiofiles>=24.1.0
Requires-Dist: aiogram-media-group>=0.5.1
Requires-Dist: aiogram>=3.22.0
Requires-Dist: beautifulsoup4>=4.14.2
Requires-Dist: click>=8.3.1
Requires-Dist: httpx>=0.28.1
Requires-Dist: langchain-community>=0.4.1
Requires-Dist: langchain-openai>=1.0.3
Requires-Dist: langchain>=1.0.8
Requires-Dist: openai>=2.8.0
Requires-Dist: playwright>=1.56.0
Requires-Dist: project-root-finder>=1.9
Requires-Dist: python-dateutil>=2.9.0.post0
Requires-Dist: python-dotenv>=1.2.1
Requires-Dist: python-slugify>=8.0.4
Requires-Dist: pytz>=2025.2
Requires-Dist: pyyaml>=6.0.3
Requires-Dist: sulguk>=0.11.1
Requires-Dist: supabase>=2.24.0
Requires-Dist: telegramify-markdown>=0.5.4
Requires-Dist: trafilatura>=2.0.0
